bitcoin_notification_f/__init__.py
bitcoin_notification_f/bitcoin_price_notification.py
bitcoin_notification_f-1.0.4.dist-info/LICENSE
bitcoin_notification_f-1.0.4.dist-info/METADATA
bitcoin_notification_f-1.0.4.dist-info/WHEEL
bitcoin_notification_f-1.0.4.dist-info/entry_points.txt
bitcoin_notification_f-1.0.4.dist-info/top_level.txt
bitcoin_notification_f-1.0.4.dist-info/RECORD
