Metadata-Version: 2.1
Name: bitcoin-notification-f
Version: 1.0.4
Summary: BITCOIN PRICE NOTIFICATION
Home-page: https://github.com/fariya-banu234-au7/python_project
Author: Fariya Banu
Author-email: fariyabanu234@gmail.com
License: MIT
Platform: UNKNOWN
Classifier: License :: OSI Approved :: MIT License
Classifier: Programming Language :: Python :: 3
Classifier: Programming Language :: Python :: 3.7
Requires-Dist: requests
Requires-Dist: datetime
